smizip/__init__.py
smizip/smizip.py
smizip/scripts/__init__.py
smizip/scripts/add_char_to_ngrams.py
smizip/scripts/compress.py
smizip/scripts/find_best_ngrams.py
smizip-2.0.1.dist-info/LICENSE
smizip-2.0.1.dist-info/METADATA
smizip-2.0.1.dist-info/WHEEL
smizip-2.0.1.dist-info/entry_points.txt
smizip-2.0.1.dist-info/top_level.txt
smizip-2.0.1.dist-info/RECORD
