Metadata-Version: 2.2
Name: smizip
Version: 2.0.1
Summary: An implementation of Roger Sayle's SmiZip algorithm for compressing short strings
License: MIT License
Project-URL: Homepage, https://github.com/baoilleach/smizip
Keywords: chemistry,cheminformatics,SMILES,compression,zip
License-File: LICENSE
Requires-Dist: pyahocorasick>=1.4.4
